scCausalVI/__init__.py
scCausalVI/data/__init__.py
scCausalVI/data/utils.py
scCausalVI/data/dataloaders/__init__.py
scCausalVI/data/dataloaders/data_splitting.py
scCausalVI/data/dataloaders/scCausalVI_dataloader.py
scCausalVI/model/__init__.py
scCausalVI/model/scCausalVI.py
scCausalVI/model/base/__init__.py
scCausalVI/model/base/_utils.py
scCausalVI/model/base/training_mixin.py
scCausalVI/module/__init__.py
scCausalVI/module/scCausalVI.py
scCausalVI/module/utils.py
scCausalVI-0.0.11.dist-info/LICENSE
scCausalVI-0.0.11.dist-info/METADATA
scCausalVI-0.0.11.dist-info/WHEEL
scCausalVI-0.0.11.dist-info/top_level.txt
scCausalVI-0.0.11.dist-info/RECORD
