Metadata-Version: 2.1
Name: scCausalVI
Version: 0.0.11
Summary: A deep causality-aware model for disentangling treatment effects at single-cell resolution for perturbational scRNA-seq data
Home-page: https://github.com/ShaokunAn/scCausalVI/
Author: Shaokun An
Author-email: shan12@bwh.harvard.edu
Classifier: Programming Language :: Python :: 3
Classifier: License :: OSI Approved :: MIT License
Classifier: Operating System :: OS Independent
Requires-Python: >=3.9
License-File: LICENSE
Requires-Dist: scanpy >=1.9.6
Requires-Dist: torch >=2.0.0
Requires-Dist: anndata >=0.10.3
Requires-Dist: numpy <2.0,>=1.23.5
Requires-Dist: setuptools >=59.5.0
Requires-Dist: pandas >=2.1.1
Requires-Dist: matplotlib >=3.8.1
Requires-Dist: scikit-learn >=1.3.2
Requires-Dist: tqdm >=4.66.1
Requires-Dist: seaborn >=0.12.2
Requires-Dist: scipy >=1.11.3
Requires-Dist: scvi-tools >=0.16.1
Requires-Dist: pytorch-lightning >=1.5.10
Requires-Dist: gdown >=5.2.0
